horizen_fastapi_template/__init__.py
horizen_fastapi_template/_internal/__init__.py
horizen_fastapi_template/_internal/database/__init__.py
horizen_fastapi_template/_internal/database/basic_api.py
horizen_fastapi_template/_internal/database/ftp_client.py
horizen_fastapi_template/_internal/database/kube_client.py
horizen_fastapi_template/_internal/middlewares/__init__.py
horizen_fastapi_template/_internal/middlewares/exception.py
horizen_fastapi_template/_internal/middlewares/log_request.py
horizen_fastapi_template/_internal/middlewares/time_request.py
horizen_fastapi_template/_internal/models/__init__.py
horizen_fastapi_template/_internal/models/handler.py
horizen_fastapi_template/_internal/routes/__init__.py
horizen_fastapi_template/_internal/routes/metrics.py
horizen_fastapi_template/_internal/routes/probes.py
horizen_fastapi_template/_internal/routes/swagger.py
horizen_fastapi_template/_internal/tasks/__init__.py
horizen_fastapi_template/_internal/tasks/uptime.py
horizen_fastapi_template/_internal/utils/__init__.py
horizen_fastapi_template/_internal/utils/config.py
horizen_fastapi_template/_internal/utils/logger.py
horizen_fastapi_template-0.1.1.dist-info/licenses/LICENSE
temp/__init__.py
temp/main.py
horizen_fastapi_template-0.1.1.dist-info/METADATA
horizen_fastapi_template-0.1.1.dist-info/WHEEL
horizen_fastapi_template-0.1.1.dist-info/top_level.txt
horizen_fastapi_template-0.1.1.dist-info/RECORD
