Metadata-Version: 2.4
Name: horizen-fastapi-template
Version: 0.1.1
Summary: A reusable FastAPI application factory
Author: Chaim Mendelson and Yehonatan Magen
License:                                  Apache License
Requires-Python: >=3.10
License-File: LICENSE
Requires-Dist: aioftp>=0.21
Requires-Dist: fastapi>=0.110
Requires-Dist: httpx>=0.24
Requires-Dist: kubernetes-asyncio>=29.0
Requires-Dist: loguru>=0.7
Requires-Dist: prometheus-client>=0.17
Requires-Dist: pydantic>=2.0
Requires-Dist: pydantic-settings>=2.0
Dynamic: license-file
